<soap:Envelope xmlns:soap="http://schemas.xmlsoap.org/soap/envelope/">
  <soap:Body>
    <ns2:requestExportDataResponse xmlns:ns2="http://export.its.dhl.com/">
      <return>
        <dataProviderDetails>
          <dataProviderType>RFID_SENSOR</dataProviderType>
          <gsmSensorDetails />
          <rfidReaderHardware>
            <mobileComputerManufacturer>Motorola</mobileComputerManufacturer>
            <mobileComputerSerialNumber>14052521402651</mobileComputerSerialNumber>
            <mobileComputerType>MC65</mobileComputerType>
            <rfidAntennaFirmwareVersion>2.6.0.240</rfidAntennaFirmwareVersion>
            <rfidAntennaHardwareVersion>Ratel</rfidAntennaHardwareVersion>
            <rfidAntennaManufacturer>TSL UK Ltd.</rfidAntennaManufacturer>
            <rfidAntennaRegion>ETSI</rfidAntennaRegion>
            <rfidAntennaSerialNumber>1119-01-003152</rfidAntennaSerialNumber>
            <rfidAntennaType>ETSI</rfidAntennaType>
            <rfidReaderType>DHL Mobile Reader</rfidReaderType>
          </rfidReaderHardware>
          <rfidReaderSoftware>
            <applicationType>DHL Mobile Reader Software</applicationType>
            <softwareVersion>2.2.0.0</softwareVersion>
          </rfidReaderSoftware>
          <rfidSensorDetails>
            <rfidSensorFirmwareVersion>1.6</rfidSensorFirmwareVersion>
            <rfidSensorHardwareVersion>2.3</rfidSensorHardwareVersion>
            <rfidSensorManufacturer>CAEN</rfidSensorManufacturer>
            <rfidSensorType>DHL SmartSensor RFID</rfidSensorType>
          </rfidSensorDetails>
        </dataProviderDetails>
        <id>496313</id>
        <measurements>
          <alertData>
            <memoryAlerts>
              <id>1724525</id>
              <number>0</number>
              <seen>0</seen>
              <type>MEMORY</type>
            </memoryAlerts>
            <powerAlerts>
              <id>1732715</id>
              <number>0</number>
              <seen>0</seen>
              <type>POWER</type>
            </powerAlerts>
            <temperatureAlerts>
              <id>16329712</id>
              <number>0</number>
              <seen>0</seen>
              <type>TEMPERATURE</type>
              <value>-10.0</value>
              <above>false</above>
              <count>0</count>
              <inRow>false</inRow>
            </temperatureAlerts>
            <temperatureAlerts>
              <id>16329713</id>
              <number>1</number>
              <seen>0</seen>
              <type>TEMPERATURE</type>
              <value>0.0</value>
              <above>false</above>
              <count>0</count>
              <inRow>false</inRow>
            </temperatureAlerts>
            <temperatureAlerts>
              <id>16329714</id>
              <number>2</number>
              <seen>0</seen>
              <type>TEMPERATURE</type>
              <value>2.0</value>
              <above>false</above>
              <count>0</count>
              <inRow>false</inRow>
            </temperatureAlerts>
            <temperatureAlerts>
              <id>16329715</id>
              <number>3</number>
              <seen>0</seen>
              <type>TEMPERATURE</type>
              <value>30.0</value>
              <above>false</above>
              <count>0</count>
              <inRow>false</inRow>
            </temperatureAlerts>
            <temperatureAlerts>
              <id>16329716</id>
              <number>4</number>
              <seen>0</seen>
              <type>TEMPERATURE</type>
              <value>40.0</value>
              <above>false</above>
              <count>0</count>
              <inRow>false</inRow>
            </temperatureAlerts>
            <temperatureAlerts>
              <id>16329717</id>
              <number>5</number>
              <seen>0</seen>
              <type>TEMPERATURE</type>
              <value>70.0</value>
              <above>false</above>
              <count>0</count>
              <inRow>false</inRow>
            </temperatureAlerts>
          </alertData>
          <bizSteps>
            <bizStepId>1</bizStepId>
            <id>1744278</id>
            <location>DGF BRU</location>
            <time>2015-12-08T20:38:37+01:00</time>
          </bizSteps>
          <histogramData>
            <temperatureHistogram>
              <count>0</count>
              <entryId>16432308</entryId>
              <interval>10</interval>
              <value>-10.0</value>
            </temperatureHistogram>
            <temperatureHistogram>
              <count>0</count>
              <entryId>16432309</entryId>
              <interval>10</interval>
              <value>0.0</value>
            </temperatureHistogram>
            <temperatureHistogram>
              <count>0</count>
              <entryId>16432310</entryId>
              <interval>10</interval>
              <value>2.0</value>
            </temperatureHistogram>
            <temperatureHistogram>
              <count>1</count>
              <entryId>16432311</entryId>
              <interval>10</interval>
              <value>30.0</value>
            </temperatureHistogram>
            <temperatureHistogram>
              <count>0</count>
              <entryId>16432312</entryId>
              <interval>10</interval>
              <value>40.0</value>
            </temperatureHistogram>
            <temperatureHistogram>
              <count>0</count>
              <entryId>16432313</entryId>
              <interval>10</interval>
              <value>70.0</value>
            </temperatureHistogram>
          </histogramData>
          <historyData>
            <temperatureHistory>
              <entryId>129575775</entryId>
              <seen>false</seen>
              <time>2015-12-08T20:40:22+01:00</time>
              <maxTemp>0.0</maxTemp>
              <minTemp>20.625</minTemp>
            </temperatureHistory>
          </historyData>
        </measurements>
        <nextExportId>496320</nextExportId>
        <shipmentDetails>
          <companyName>Brussels</companyName>
          <groupName>Thermonet</groupName>
          <sensorId>300EFE2F94D0FB000000D226</sensorId>
          <shipmentId>946071</shipmentId>
          <shipmentNo>H6SF1906   +Y0001+</shipmentNo>
        </shipmentDetails>
      </return>
    </ns2:requestExportDataResponse>
  </soap:Body>
</soap:Envelope>
